core/__init__.py
core/bootstrap.py
core/compare.py
core/find.py
core/main.py
core/open.py
core/retry_failed.py
core/show_dependencies.py
test/__init__.py
test/test.py
test/integration/__init__.py
test/integration/base.py
utils/__init__.py
utils/logging.py
utils/ui.py
dbt_helper-0.5.0.dist-info/LICENSE
dbt_helper-0.5.0.dist-info/METADATA
dbt_helper-0.5.0.dist-info/WHEEL
dbt_helper-0.5.0.dist-info/entry_points.txt
dbt_helper-0.5.0.dist-info/top_level.txt
dbt_helper-0.5.0.dist-info/RECORD
