Metadata-Version: 2.1
Name: dbt-helper
Version: 0.5.0
Summary: dbt-helper is a command line tool to help ease dbt development and database management
Home-page: https://github.com/mikekaminsky/dbt-helper
Author: Michael Kaminsky
Author-email: michael@kaminsky.rocks
License: UNKNOWN
Platform: UNKNOWN
Requires-Dist: dbt
